enhanced_versioning/__init__.py
enhanced_versioning/base_version.py
enhanced_versioning/nonsemantic_version.py
enhanced_versioning/semantic_version.py
enhanced_versioning/test_nonsemantic_version.py
enhanced_versioning/test_semantic_version.py
enhanced_versioning-0.3.0.dist-info/LICENSE-MIT
enhanced_versioning-0.3.0.dist-info/METADATA
enhanced_versioning-0.3.0.dist-info/WHEEL
enhanced_versioning-0.3.0.dist-info/top_level.txt
enhanced_versioning-0.3.0.dist-info/RECORD
