Metadata-Version: 2.1
Name: enhanced-versioning
Version: 0.3.0
Summary: Versioning system with semantic versioning and generic version formats
Home-page: http://github.com/loganmackenzie/enhanced-versioning
Author: Logan MacKenzie
Author-email: loganmackenzie1@gmail.com
Maintainer: Logan MacKenzie
Maintainer-email: loganmackenzie1@gmail.com
License: MIT
Keywords: semver semantic version versioning versions
Platform: UNKNOWN
Classifier: Development Status :: 3 - Alpha
Classifier: Intended Audience :: Developers
Classifier: Topic :: Utilities
